tf_quant_finance/__init__.py
tf_quant_finance/black_scholes/__init__.py
tf_quant_finance/black_scholes/brownian_bridge.py
tf_quant_finance/black_scholes/crr_binomial_tree.py
tf_quant_finance/black_scholes/implied_vol_approximation.py
tf_quant_finance/black_scholes/implied_vol_lib.py
tf_quant_finance/black_scholes/implied_vol_newton_root.py
tf_quant_finance/black_scholes/implied_vol_utils.py
tf_quant_finance/black_scholes/vanilla_prices.py
tf_quant_finance/black_scholes/variance_swaps.py
tf_quant_finance/black_scholes/approximations/__init__.py
tf_quant_finance/black_scholes/approximations/american_option.py
tf_quant_finance/datetime/__init__.py
tf_quant_finance/datetime/bounded_holiday_calendar.py
tf_quant_finance/datetime/constants.py
tf_quant_finance/datetime/date_tensor.py
tf_quant_finance/datetime/date_utils.py
tf_quant_finance/datetime/daycounts.py
tf_quant_finance/datetime/holiday_calendar.py
tf_quant_finance/datetime/holiday_calendar_factory.py
tf_quant_finance/datetime/holiday_utils.py
tf_quant_finance/datetime/schedules.py
tf_quant_finance/datetime/tensor_wrapper.py
tf_quant_finance/datetime/unbounded_holiday_calendar.py
tf_quant_finance/datetime/periods/__init__.py
tf_quant_finance/datetime/periods/period_tensors.py
tf_quant_finance/experimental/__init__.py
tf_quant_finance/experimental/io.py
tf_quant_finance/experimental/finite_difference/__init__.py
tf_quant_finance/experimental/finite_difference/methods.py
tf_quant_finance/experimental/instruments/__init__.py
tf_quant_finance/experimental/instruments/bond.py
tf_quant_finance/experimental/instruments/cap_floor.py
tf_quant_finance/experimental/instruments/cashflow_stream.py
tf_quant_finance/experimental/instruments/cms_swap.py
tf_quant_finance/experimental/instruments/eurodollar_futures.py
tf_quant_finance/experimental/instruments/floating_rate_note.py
tf_quant_finance/experimental/instruments/forward_rate_agreement.py
tf_quant_finance/experimental/instruments/interest_rate_swap.py
tf_quant_finance-0.0.1.dev34.dist-info/LICENSE
tf_quant_finance-0.0.1.dev34.dist-info/METADATA
tf_quant_finance-0.0.1.dev34.dist-info/WHEEL
tf_quant_finance-0.0.1.dev34.dist-info/top_level.txt
tf_quant_finance-0.0.1.dev34.dist-info/RECORD
